by_sample_migration.py
by_sample_migration-0.1.0.dist-info/METADATA
by_sample_migration-0.1.0.dist-info/WHEEL
by_sample_migration-0.1.0.dist-info/RECORD
